myndapp/api/database.py
myndapp/api/dependencies.py
myndapp/api/image_store.py
myndapp/api/server.py
myndapp/api/settings.py
myndapp/api/routers/__init__.py
myndapp/api/routers/images.py
myndapp/api/routers/tasks.py
myndapp/api/routers/cameras/__init__.py
myndapp/api/routers/cameras/camera_base.py
myndapp/api/routers/cameras/camera_tasks.py
myndapp/api/routers/chunks/__init__.py
myndapp/api/routers/chunks/chunk_crud.py
myndapp/api/routers/stereo/__init__.py
myndapp/api/routers/stereo/stereo_base.py
myndapp/api/routers/stereo/stereo_tasks.py
myndapp/cli/celery.py
myndapp/cli/database.py
myndapp/cli/document.py
myndapp/cli/group.py
myndapp/cli/main.py
myndapp/cli/server.py
myndapp/cli/image_processing/__init__.py
myndapp/cli/image_processing/group.py
myndapp/distributed/worker.py
myndapp/distributed/stereo_tasks/__init__.py
myndapp/distributed/stereo_tasks/stereo_export.py
myndapp/distributed/stereo_tasks/stereo_processing.py
mynd_backend-0.1.0.dist-info/METADATA
mynd_backend-0.1.0.dist-info/WHEEL
mynd_backend-0.1.0.dist-info/entry_points.txt
mynd_backend-0.1.0.dist-info/RECORD
